sqlalchemy_asyncselect/__init__.py
sqlalchemy_sugar/__init__.py
sqlalchemy_sugar-0.1.1.dist-info/LICENSE
sqlalchemy_sugar-0.1.1.dist-info/METADATA
sqlalchemy_sugar-0.1.1.dist-info/WHEEL
sqlalchemy_sugar-0.1.1.dist-info/top_level.txt
sqlalchemy_sugar-0.1.1.dist-info/RECORD
