Metadata-Version: 2.1
Name: sqlalchemy-sugar
Version: 0.1.1
Summary: select/delete wrapper for SQLAlchemy Asyncio
Home-page: https://github.com/yosshy/sqlalchemy-sugar
Author: Akira Yoshiyama
Author-email: akirayoshiyama@gmail.com
License: Copyright (c) 2020, Akira Yoshiyama
